[
  {
    "description": "    Como usuário, desejo acessar a listagem\n    Para que possa visualizar meus dados de cadastro",
    "keyword": "Feature",
    "name": "Listagem",
    "line": 1,
    "id": "listagem",
    "tags": [],
    "uri": "Listagem.feature",
    "elements": [
      {
        "id": "listagem;listagem-sem-registros",
        "keyword": "Scenario",
        "line": 6,
        "name": "Listagem sem registros",
        "tags": [],
        "type": "scenario",
        "steps": [
          {
            "arguments": [],
            "keyword": "Given ",
            "line": 7,
            "name": "que o site não possui registros",
            "result": {
              "status": "passed",
              "duration": 23525000000
            }
          },
          {
            "arguments": [],
            "keyword": "When ",
            "line": 8,
            "name": "acessar a listagem",
            "result": {
              "status": "passed",
              "duration": 1781000000
            }
          },
          {
            "arguments": [],
            "keyword": "Then ",
            "line": 9,
            "name": "devo visualizar a listagem vazia",
            "result": {
              "status": "passed",
              "duration": 42000000
            }
          }
        ]
      },
      {
        "id": "listagem;listagem-com-apenas-um-registro",
        "keyword": "Scenario",
        "line": 11,
        "name": "Listagem com apenas um registro",
        "tags": [],
        "type": "scenario",
        "steps": [
          {
            "arguments": [],
            "keyword": "Given ",
            "line": 12,
            "name": "que o site possui apenas um registro",
            "result": {
              "status": "passed",
              "duration": 281000000
            }
          },
          {
            "arguments": [],
            "keyword": "When ",
            "line": 13,
            "name": "acessar a listagem",
            "result": {
              "status": "passed",
              "duration": 1393000000
            }
          },
          {
            "arguments": [],
            "keyword": "Then ",
            "line": 14,
            "name": "devo visualizar apenas um registro",
            "result": {
              "status": "passed",
              "duration": 68000000
            }
          }
        ]
      }
    ]
  }
]